logging_addons.py
logging_addons-0.5.3.dist-info/entry_points.txt
logging_addons-0.5.3.dist-info/LICENSE
logging_addons-0.5.3.dist-info/WHEEL
logging_addons-0.5.3.dist-info/METADATA
logging_addons-0.5.3.dist-info/RECORD
