Metadata-Version: 2.1
Name: logging_addons
Version: 0.5.3
Summary: Add-ons for the logging standard library
Keywords: logging
Author: netcreator
Requires-Python: >=3.7
Classifier: Programming Language :: Python :: 3
Classifier: License :: OSI Approved :: MIT License
Classifier: Operating System :: OS Independent
Project-URL: Documentation, http://bitbucket.org/netcreator/logging_addons/src/master/docs/README.md
Project-URL: Home, http://bitbucket.org/netcreator/logging_addons
